invoiceJB/__init__.py
invoiceJB/invoice.py
invoiceJB-0.1.0.dist-info/LICENSE
invoiceJB-0.1.0.dist-info/METADATA
invoiceJB-0.1.0.dist-info/WHEEL
invoiceJB-0.1.0.dist-info/top_level.txt
invoiceJB-0.1.0.dist-info/RECORD
