Metadata-Version: 2.1
Name: invoiceJB
Version: 0.1.0
Summary: Taiwan invoice number
Home-page: https://github.com/JBProgramNotes/invoiceJB
Author: JamesBang
Author-email: JBProgramNotes@gmail.com
License: UNKNOWN
Keywords: invoice
Platform: UNKNOWN
Classifier: Programming Language :: Python :: 3
Classifier: License :: OSI Approved :: MIT License
License-File: LICENSE
